accelbyte_py_sdk/api/leaderboard/__init__.py
accelbyte_py_sdk/api/leaderboard/errors.py
accelbyte_py_sdk/api/leaderboard/models/__init__.py
accelbyte_py_sdk/api/leaderboard/models/models_archive_leaderboard_req.py
accelbyte_py_sdk/api/leaderboard/models/models_archive_leaderboard_signed_url_response.py
accelbyte_py_sdk/api/leaderboard/models/models_bulk_user_i_ds_request.py
accelbyte_py_sdk/api/leaderboard/models/models_bulk_user_ranking_response_v3.py
accelbyte_py_sdk/api/leaderboard/models/models_daily_config.py
accelbyte_py_sdk/api/leaderboard/models/models_delete_bulk_leaderboard_failed_resp.py
accelbyte_py_sdk/api/leaderboard/models/models_delete_bulk_leaderboard_success_resp.py
accelbyte_py_sdk/api/leaderboard/models/models_delete_bulk_leaderboards_req.py
accelbyte_py_sdk/api/leaderboard/models/models_delete_bulk_leaderboards_resp.py
accelbyte_py_sdk/api/leaderboard/models/models_get_all_leaderboard_configs_public_resp.py
accelbyte_py_sdk/api/leaderboard/models/models_get_all_leaderboard_configs_public_resp_v3.py
accelbyte_py_sdk/api/leaderboard/models/models_get_all_leaderboard_configs_resp.py
accelbyte_py_sdk/api/leaderboard/models/models_get_all_leaderboard_configs_resp_v3.py
accelbyte_py_sdk/api/leaderboard/models/models_get_all_user_leaderboards_resp.py
accelbyte_py_sdk/api/leaderboard/models/models_get_all_user_leaderboards_resp_v3.py
accelbyte_py_sdk/api/leaderboard/models/models_get_hidden_user_response.py
accelbyte_py_sdk/api/leaderboard/models/models_get_leaderboard_config_public_resp.py
accelbyte_py_sdk/api/leaderboard/models/models_get_leaderboard_config_public_resp_v3.py
accelbyte_py_sdk/api/leaderboard/models/models_get_leaderboard_config_resp.py
accelbyte_py_sdk/api/leaderboard/models/models_get_leaderboard_config_resp_v3.py
accelbyte_py_sdk/api/leaderboard/models/models_get_leaderboard_ranking_resp.py
accelbyte_py_sdk/api/leaderboard/models/models_get_user_visibility_response.py
accelbyte_py_sdk_service_leaderboard-0.27.0.dist-info/METADATA
accelbyte_py_sdk_service_leaderboard-0.27.0.dist-info/WHEEL
accelbyte_py_sdk_service_leaderboard-0.27.0.dist-info/top_level.txt
accelbyte_py_sdk_service_leaderboard-0.27.0.dist-info/RECORD
