Metadata-Version: 2.4
Name: accelbyte-py-sdk-service-leaderboard
Version: 0.27.0
Summary: AccelByte Python SDK - AccelByte Gaming Services Leaderboard Service
Requires-Python: >=3.9
Requires-Dist: accelbyte-py-sdk-core
